[
  {
    "name": "Process Start",
    "start": 1606742707624,
    "end": 1606742708361,
    "duration": 737,
    "pid": 1652,
    "index": 0
  },
  {
    "name": "Application Start",
    "start": 1606742708361,
    "end": 1606742709372,
    "duration": 1011,
    "pid": 1652,
    "index": 1
  },
  {
    "name": "Load Plugin",
    "start": 1606742708366,
    "end": 1606742708389,
    "duration": 23,
    "pid": 1652,
    "index": 2
  },
  {
    "name": "Load Config",
    "start": 1606742708389,
    "end": 1606742708419,
    "duration": 30,
    "pid": 1652,
    "index": 3
  },
  {
    "name": "Require(0) config/config.default.js",
    "start": 1606742708390,
    "end": 1606742708391,
    "duration": 1,
    "pid": 1652,
    "index": 4
  },
  {
    "name": "Require(1) node_modules/egg-session/config/config.default.js",
    "start": 1606742708393,
    "end": 1606742708393,
    "duration": 0,
    "pid": 1652,
    "index": 5
  },
  {
    "name": "Require(2) node_modules/egg-security/config/config.default.js",
    "start": 1606742708394,
    "end": 1606742708394,
    "duration": 0,
    "pid": 1652,
    "index": 6
  },
  {
    "name": "Require(3) node_modules/egg-jsonp/config/config.default.js",
    "start": 1606742708395,
    "end": 1606742708396,
    "duration": 1,
    "pid": 1652,
    "index": 7
  },
  {
    "name": "Require(4) node_modules/egg-onerror/config/config.default.js",
    "start": 1606742708396,
    "end": 1606742708397,
    "duration": 1,
    "pid": 1652,
    "index": 8
  },
  {
    "name": "Require(5) node_modules/egg-i18n/config/config.default.js",
    "start": 1606742708398,
    "end": 1606742708399,
    "duration": 1,
    "pid": 1652,
    "index": 9
  },
  {
    "name": "Require(6) node_modules/egg-watcher/config/config.default.js",
    "start": 1606742708400,
    "end": 1606742708401,
    "duration": 1,
    "pid": 1652,
    "index": 10
  },
  {
    "name": "Require(7) node_modules/egg-schedule/config/config.default.js",
    "start": 1606742708402,
    "end": 1606742708403,
    "duration": 1,
    "pid": 1652,
    "index": 11
  },
  {
    "name": "Require(8) node_modules/egg-multipart/config/config.default.js",
    "start": 1606742708404,
    "end": 1606742708404,
    "duration": 0,
    "pid": 1652,
    "index": 12
  },
  {
    "name": "Require(9) node_modules/egg-development/config/config.default.js",
    "start": 1606742708405,
    "end": 1606742708406,
    "duration": 1,
    "pid": 1652,
    "index": 13
  },
  {
    "name": "Require(10) node_modules/egg-logrotator/config/config.default.js",
    "start": 1606742708406,
    "end": 1606742708407,
    "duration": 1,
    "pid": 1652,
    "index": 14
  },
  {
    "name": "Require(11) node_modules/egg-static/config/config.default.js",
    "start": 1606742708408,
    "end": 1606742708408,
    "duration": 0,
    "pid": 1652,
    "index": 15
  },
  {
    "name": "Require(12) node_modules/egg-view/config/config.default.js",
    "start": 1606742708409,
    "end": 1606742708409,
    "duration": 0,
    "pid": 1652,
    "index": 16
  },
  {
    "name": "Require(13) node_modules/egg-view-nunjucks/config/config.default.js",
    "start": 1606742708410,
    "end": 1606742708410,
    "duration": 0,
    "pid": 1652,
    "index": 17
  },
  {
    "name": "Require(14) node_modules/egg-mongoose/config/config.default.js",
    "start": 1606742708411,
    "end": 1606742708411,
    "duration": 0,
    "pid": 1652,
    "index": 18
  },
  {
    "name": "Require(15) node_modules/egg/config/config.default.js",
    "start": 1606742708412,
    "end": 1606742708412,
    "duration": 0,
    "pid": 1652,
    "index": 19
  },
  {
    "name": "Require(16) config/config.default.js",
    "start": 1606742708413,
    "end": 1606742708413,
    "duration": 0,
    "pid": 1652,
    "index": 20
  },
  {
    "name": "Require(17) node_modules/egg-security/config/config.local.js",
    "start": 1606742708414,
    "end": 1606742708414,
    "duration": 0,
    "pid": 1652,
    "index": 21
  },
  {
    "name": "Require(18) node_modules/egg-watcher/config/config.local.js",
    "start": 1606742708415,
    "end": 1606742708415,
    "duration": 0,
    "pid": 1652,
    "index": 22
  },
  {
    "name": "Require(19) node_modules/egg-view/config/config.local.js",
    "start": 1606742708417,
    "end": 1606742708417,
    "duration": 0,
    "pid": 1652,
    "index": 23
  },
  {
    "name": "Require(20) node_modules/egg-view-nunjucks/config/config.local.js",
    "start": 1606742708418,
    "end": 1606742708418,
    "duration": 0,
    "pid": 1652,
    "index": 24
  },
  {
    "name": "Require(21) node_modules/egg/config/config.local.js",
    "start": 1606742708419,
    "end": 1606742708419,
    "duration": 0,
    "pid": 1652,
    "index": 25
  },
  {
    "name": "Load extend/application.js",
    "start": 1606742708420,
    "end": 1606742708464,
    "duration": 44,
    "pid": 1652,
    "index": 26
  },
  {
    "name": "Require(22) node_modules/egg-session/app/extend/application.js",
    "start": 1606742708421,
    "end": 1606742708421,
    "duration": 0,
    "pid": 1652,
    "index": 27
  },
  {
    "name": "Require(23) node_modules/egg-security/app/extend/application.js",
    "start": 1606742708422,
    "end": 1606742708423,
    "duration": 1,
    "pid": 1652,
    "index": 28
  },
  {
    "name": "Require(24) node_modules/egg-jsonp/app/extend/application.js",
    "start": 1606742708423,
    "end": 1606742708425,
    "duration": 2,
    "pid": 1652,
    "index": 29
  },
  {
    "name": "Require(25) node_modules/egg-logrotator/app/extend/application.js",
    "start": 1606742708426,
    "end": 1606742708428,
    "duration": 2,
    "pid": 1652,
    "index": 30
  },
  {
    "name": "Require(26) node_modules/egg-view/app/extend/application.js",
    "start": 1606742708429,
    "end": 1606742708430,
    "duration": 1,
    "pid": 1652,
    "index": 31
  },
  {
    "name": "Require(27) node_modules/egg-view-nunjucks/app/extend/application.js",
    "start": 1606742708431,
    "end": 1606742708459,
    "duration": 28,
    "pid": 1652,
    "index": 32
  },
  {
    "name": "Load extend/request.js",
    "start": 1606742708464,
    "end": 1606742708473,
    "duration": 9,
    "pid": 1652,
    "index": 33
  },
  {
    "name": "Require(28) node_modules/egg/app/extend/request.js",
    "start": 1606742708468,
    "end": 1606742708469,
    "duration": 1,
    "pid": 1652,
    "index": 34
  },
  {
    "name": "Load extend/response.js",
    "start": 1606742708473,
    "end": 1606742708484,
    "duration": 11,
    "pid": 1652,
    "index": 35
  },
  {
    "name": "Require(29) node_modules/egg/app/extend/response.js",
    "start": 1606742708478,
    "end": 1606742708480,
    "duration": 2,
    "pid": 1652,
    "index": 36
  },
  {
    "name": "Load extend/context.js",
    "start": 1606742708484,
    "end": 1606742708552,
    "duration": 68,
    "pid": 1652,
    "index": 37
  },
  {
    "name": "Require(30) node_modules/egg-security/app/extend/context.js",
    "start": 1606742708485,
    "end": 1606742708496,
    "duration": 11,
    "pid": 1652,
    "index": 38
  },
  {
    "name": "Require(31) node_modules/egg-jsonp/app/extend/context.js",
    "start": 1606742708496,
    "end": 1606742708498,
    "duration": 2,
    "pid": 1652,
    "index": 39
  },
  {
    "name": "Require(32) node_modules/egg-i18n/app/extend/context.js",
    "start": 1606742708499,
    "end": 1606742708499,
    "duration": 0,
    "pid": 1652,
    "index": 40
  },
  {
    "name": "Require(33) node_modules/egg-multipart/app/extend/context.js",
    "start": 1606742708500,
    "end": 1606742708544,
    "duration": 44,
    "pid": 1652,
    "index": 41
  },
  {
    "name": "Require(34) node_modules/egg-view/app/extend/context.js",
    "start": 1606742708545,
    "end": 1606742708546,
    "duration": 1,
    "pid": 1652,
    "index": 42
  },
  {
    "name": "Require(35) node_modules/egg-mongoose/app/extend/context.js",
    "start": 1606742708547,
    "end": 1606742708547,
    "duration": 0,
    "pid": 1652,
    "index": 43
  },
  {
    "name": "Require(36) node_modules/egg/app/extend/context.js",
    "start": 1606742708547,
    "end": 1606742708548,
    "duration": 1,
    "pid": 1652,
    "index": 44
  },
  {
    "name": "Load extend/helper.js",
    "start": 1606742708552,
    "end": 1606742708584,
    "duration": 32,
    "pid": 1652,
    "index": 45
  },
  {
    "name": "Require(37) node_modules/egg-security/app/extend/helper.js",
    "start": 1606742708553,
    "end": 1606742708570,
    "duration": 17,
    "pid": 1652,
    "index": 46
  },
  {
    "name": "Require(38) node_modules/egg/app/extend/helper.js",
    "start": 1606742708573,
    "end": 1606742708574,
    "duration": 1,
    "pid": 1652,
    "index": 47
  },
  {
    "name": "Require(39) app/extend/helper.js",
    "start": 1606742708574,
    "end": 1606742708578,
    "duration": 4,
    "pid": 1652,
    "index": 48
  },
  {
    "name": "Load app.js",
    "start": 1606742708584,
    "end": 1606742708627,
    "duration": 43,
    "pid": 1652,
    "index": 49
  },
  {
    "name": "Require(40) node_modules/egg-session/app.js",
    "start": 1606742708584,
    "end": 1606742708585,
    "duration": 1,
    "pid": 1652,
    "index": 50
  },
  {
    "name": "Require(41) node_modules/egg-security/app.js",
    "start": 1606742708585,
    "end": 1606742708588,
    "duration": 3,
    "pid": 1652,
    "index": 51
  },
  {
    "name": "Require(42) node_modules/egg-onerror/app.js",
    "start": 1606742708588,
    "end": 1606742708597,
    "duration": 9,
    "pid": 1652,
    "index": 52
  },
  {
    "name": "Require(43) node_modules/egg-i18n/app.js",
    "start": 1606742708598,
    "end": 1606742708616,
    "duration": 18,
    "pid": 1652,
    "index": 53
  },
  {
    "name": "Require(44) node_modules/egg-watcher/app.js",
    "start": 1606742708616,
    "end": 1606742708619,
    "duration": 3,
    "pid": 1652,
    "index": 54
  },
  {
    "name": "Require(45) node_modules/egg-schedule/app.js",
    "start": 1606742708620,
    "end": 1606742708621,
    "duration": 1,
    "pid": 1652,
    "index": 55
  },
  {
    "name": "Require(46) node_modules/egg-multipart/app.js",
    "start": 1606742708622,
    "end": 1606742708622,
    "duration": 0,
    "pid": 1652,
    "index": 56
  },
  {
    "name": "Require(47) node_modules/egg-development/app.js",
    "start": 1606742708622,
    "end": 1606742708623,
    "duration": 1,
    "pid": 1652,
    "index": 57
  },
  {
    "name": "Require(48) node_modules/egg-logrotator/app.js",
    "start": 1606742708623,
    "end": 1606742708623,
    "duration": 0,
    "pid": 1652,
    "index": 58
  },
  {
    "name": "Require(49) node_modules/egg-static/app.js",
    "start": 1606742708624,
    "end": 1606742708624,
    "duration": 0,
    "pid": 1652,
    "index": 59
  },
  {
    "name": "Require(50) node_modules/egg-view-nunjucks/app.js",
    "start": 1606742708625,
    "end": 1606742708625,
    "duration": 0,
    "pid": 1652,
    "index": 60
  },
  {
    "name": "Require(51) node_modules/egg-mongoose/app.js",
    "start": 1606742708625,
    "end": 1606742708625,
    "duration": 0,
    "pid": 1652,
    "index": 61
  },
  {
    "name": "Require(52) app.js",
    "start": 1606742708626,
    "end": 1606742708627,
    "duration": 1,
    "pid": 1652,
    "index": 62
  },
  {
    "name": "Before Start in node_modules/egg-watcher/lib/init.js:15:14",
    "start": 1606742708640,
    "end": 1606742709372,
    "duration": 732,
    "pid": 1652,
    "index": 63
  },
  {
    "name": "Before Start in node_modules/egg-mongoose/lib/mongoose.js:104:7",
    "start": 1606742709117,
    "end": 1606742709370,
    "duration": 253,
    "pid": 1652,
    "index": 64
  },
  {
    "name": "Before Start in node_modules/egg-mongoose/lib/mongoose.js:52:9",
    "start": 1606742709117,
    "end": 1606742709348,
    "duration": 231,
    "pid": 1652,
    "index": 65
  },
  {
    "name": "Load Service",
    "start": 1606742709117,
    "end": 1606742709162,
    "duration": 45,
    "pid": 1652,
    "index": 66
  },
  {
    "name": "Load \"service\" to Context",
    "start": 1606742709117,
    "end": 1606742709162,
    "duration": 45,
    "pid": 1652,
    "index": 67
  },
  {
    "name": "Load Middleware",
    "start": 1606742709162,
    "end": 1606742709303,
    "duration": 141,
    "pid": 1652,
    "index": 68
  },
  {
    "name": "Load \"middlewares\" to Application",
    "start": 1606742709163,
    "end": 1606742709288,
    "duration": 125,
    "pid": 1652,
    "index": 69
  },
  {
    "name": "Load Controller",
    "start": 1606742709303,
    "end": 1606742709315,
    "duration": 12,
    "pid": 1652,
    "index": 70
  },
  {
    "name": "Load \"controller\" to Application",
    "start": 1606742709303,
    "end": 1606742709315,
    "duration": 12,
    "pid": 1652,
    "index": 71
  },
  {
    "name": "Load Router",
    "start": 1606742709315,
    "end": 1606742709318,
    "duration": 3,
    "pid": 1652,
    "index": 72
  },
  {
    "name": "Require(53) app/router.js",
    "start": 1606742709316,
    "end": 1606742709316,
    "duration": 0,
    "pid": 1652,
    "index": 73
  },
  {
    "name": "Before Start in node_modules/egg-core/lib/egg.js:303:10",
    "start": 1606742709316,
    "end": 1606742709348,
    "duration": 32,
    "pid": 1652,
    "index": 74
  },
  {
    "name": "Load \"model\" to Application",
    "start": 1606742709327,
    "end": 1606742709347,
    "duration": 20,
    "pid": 1652,
    "index": 75
  }
]